data_bench_faker/__init__.py
data_bench_faker/base.py
data_bench_faker/customer.py
data_bench_faker/data.py
data_bench_faker/transaction.py
data_bench_faker-0.5.0.dist-info/DESCRIPTION.rst
data_bench_faker-0.5.0.dist-info/METADATA
data_bench_faker-0.5.0.dist-info/RECORD
data_bench_faker-0.5.0.dist-info/WHEEL
data_bench_faker-0.5.0.dist-info/metadata.json
data_bench_faker-0.5.0.dist-info/top_level.txt
data_bench_faker-0.5.0.dist-info/zip-safe
